postgres_mcp_server.py
postgres_mcp_server-1.0.1.dist-info/METADATA
postgres_mcp_server-1.0.1.dist-info/WHEEL
postgres_mcp_server-1.0.1.dist-info/entry_points.txt
postgres_mcp_server-1.0.1.dist-info/licenses/LICENSE
postgres_mcp_server-1.0.1.dist-info/RECORD
