Metadata-Version: 2.4
Name: postgres-mcp-server
Version: 1.0.1
Summary: A Model Context Protocol server for PostgreSQL databases with SSL support
Project-URL: Homepage, https://modelcontextprotocol.io
Project-URL: Documentation, https://github.com/mcp-community/postgres-mcp-server/blob/main/README.md
Project-URL: Repository, https://github.com/mcp-community/postgres-mcp-server
Project-URL: Bug Reports, https://github.com/mcp-community/postgres-mcp-server/issues
Author-email: MCP Community <community@mcp.dev>
License: MIT
License-File: LICENSE
Keywords: ai,database,llm,mcp,model-context-protocol,postgresql
Classifier: Development Status :: 4 - Beta
Classifier: Framework :: AsyncIO
Classifier: Intended Audience :: Developers
Classifier: License :: OSI Approved :: MIT License
Classifier: Operating System :: OS Independent
Classifier: Programming Language :: Python :: 3
Classifier: Programming Language :: Python :: 3.8
Classifier: Programming Language :: Python :: 3.9
Classifier: Programming Language :: Python :: 3.10
Classifier: Programming Language :: Python :: 3.11
Classifier: Programming Language :: Python :: 3.12
Classifier: Topic :: Database
Classifier: Topic :: Scientific/Engineering :: Artificial Intelligence
Classifier: Topic :: Software Development :: Libraries :: Python Modules
Requires-Python: >=3.8
Requires-Dist: mcp>=1.0.1
Requires-Dist: psycopg2-binary>=2.9.7
